flickr_archiver
